LICENSE
README.md
setup.py
charactergpt_prompts/__init__.py
charactergpt_prompts/prompt_generator.py
charactergpt_prompts.egg-info/PKG-INFO
charactergpt_prompts.egg-info/SOURCES.txt
charactergpt_prompts.egg-info/dependency_links.txt
charactergpt_prompts.egg-info/top_level.txt
charactergpt_prompts/additional_data/character_gpt_errors.py
charactergpt_prompts/additional_data/debug_mode_prompt
charactergpt_prompts/additional_data/prompt_finish
charactergpt_prompts/character_examples/Alys
charactergpt_prompts/character_examples/Ami
charactergpt_prompts/character_examples/Sakura
charactergpt_prompts/jailbreaks/default.txt