Metadata-Version: 2.1
Name: charactergpt-prompts
Version: 0.1.0
Summary: This library is designed to make the creation of characters for roll-play in ChatGPT much easier
Home-page: https://github.com/hikki-e/CharacterGPT
Author: Hikki-e
Author-email: zmk383@gmail.com
Classifier: Programming Language :: Python :: 3
Classifier: License :: OSI Approved :: MIT License
Classifier: Operating System :: OS Independent
License-File: LICENSE
